[
    {
        "Name": "Dungeon of Souls",
        "Boss": "Wadon",

        "Floors": 10,
        "BossFloor": 10,
        "SavePoints": 2,

        "DungeonHint": "God of Souls",

        "RequiredQuestID": 10,

        "DungeonBackground": "./events/Models/json_prefabs/weapon_png/Dungeon-background.jpeg",
        "Image": "attachment://Dungeon-background.jpeg",

        "Floor1": [ 79, 79, 61, 61 ],
        "Floor2": [ 39, 39, 39, 61, 61 ],
        "Floor3": [ 47, 47, 47, 47, 47 ],
        "Floor4": [ 45, 45, 76 ],

        "Floor5": [ 45, 45, 45, 45, 45, 76, 76 ],

        "Floor6": [ 76, 76, 95 ],
        "Floor7": [ 76, 76, 76, 95, 95 ],
        "Floor8": [ 76, 76, 76, 76, 95, 95, 95 ],
        "Floor9": [ 45, 45, 45, 45, 45, 45, 45, 45, 76, 76, 95, 95, 95, 95, 59 ],

        "DungeonID": 1,
        "DungeonSpecID": 0
    },
    {
        "Name": "Dungeon of Darkness",
        "Boss": "Dyvulla",

        "Floors": 15,
        "BossFloor": 15,
        "SavePoints": 3,

        "DungeonHint": "Goddess of the Dark",

        "RequiredQuestID": 15,

        "DungeonBackground": "./events/Models/json_prefabs/weapon_png/Dungeon-background.jpeg",
        "Image": "attachment://Dungeon-background.jpeg",

        "Floor1": [ 3 ],
        "Floor2": [ 2 ],
        "Floor3": [ 4 ],
        "Floor4": [ 3 ],

        "Floor5": [ 5 ],

        "Floor6": [ 4 ],
        "Floor7": [ 5 ],
        "Floor8": [ 6 ],
        "Floor9": [ 7 ],

        "Floor10": [ 3 ],

        "Floor11": [ 2 ],
        "Floor12": [ 4 ],
        "Floor13": [ 3 ],
        "Floor14": [ 5 ],

        "DungeonID": 2,
        "DungeonSpecID": 0
    }
]
